pacer_builder/.git/COMMIT_EDITMSG
pacer_builder/.git/HEAD
pacer_builder/.git/config
pacer_builder/.git/description
pacer_builder/.git/hooks/applypatch-msg.sample
pacer_builder/.git/hooks/commit-msg.sample
pacer_builder/.git/hooks/post-update.sample
pacer_builder/.git/hooks/pre-applypatch.sample
pacer_builder/.git/hooks/pre-commit.sample
pacer_builder/.git/hooks/pre-push.sample
pacer_builder/.git/hooks/pre-rebase.sample
pacer_builder/.git/hooks/pre-receive.sample
pacer_builder/.git/hooks/prepare-commit-msg.sample
pacer_builder/.git/hooks/update.sample
pacer_builder/.git/index
pacer_builder/.git/info/exclude
pacer_builder/.git/logs/HEAD
pacer_builder/.git/logs/refs/heads/main
pacer_builder/.git/logs/refs/remotes/origin/main
pacer_builder/.git/objects/02/af89416e51cc1f83b4a0799bda05c0980f86bb
pacer_builder/.git/objects/06/0dddc5892d0d1362f4345417517cd215ddcb3a
pacer_builder/.git/objects/09/1e301dfa291850cdc0cd82cb43f1efa10b49d4
pacer_builder/.git/objects/0b/8194904452a320fff7f57e11cef77db4173228
pacer_builder/.git/objects/10/5ce2da2d6447d11dfe32bfb846c3d5b199fc99
pacer_builder/.git/objects/12/c29769446b5a5523e167dfc56754b2b7bfedb6
pacer_builder/.git/objects/13/3e40a3a8318eec640204c0c1a1c8b0481b21df
pacer_builder/.git/objects/1a/bc67b90d4824c9c32be5f765e10ff8d54ed03d
pacer_builder/.git/objects/1a/c2c15e31f6c7a6eca3b2489bc31d690d4cf876
pacer_builder/.git/objects/20/47c441e52ca85fc04206a321c6eac50e2a3a22
pacer_builder/.git/objects/22/477b63f1f1899d0fc5fb9a99475a4e9faa72be
pacer_builder/.git/objects/22/b2ee92fffcc5c81438bc131bd409323fba4472
pacer_builder/.git/objects/23/82f086df8328af394a4024aee0230bed62d453
pacer_builder/.git/objects/29/1ebd66f1c316cadbaea42519b5698daa7a7961
pacer_builder/.git/objects/29/9321170a980b32315449b6a9ef98c01ee11ae1
pacer_builder/.git/objects/29/b9ea345c360f34bca37eed2c953a4a5f13d96d
pacer_builder/.git/objects/2a/27d933264abc7c7d694494b5ffd2cc4462408d
pacer_builder/.git/objects/2a/99f45685e3fa0e5f159e6c3ccc7191029074dc
pacer_builder-0.3.1.dist-info/METADATA
pacer_builder-0.3.1.dist-info/WHEEL
pacer_builder-0.3.1.dist-info/entry_points.txt
pacer_builder-0.3.1.dist-info/RECORD
